lastpass_hibp/__init__.py
lastpass_hibp/hibp_checker.py
lastpass_hibp/lastpass_wrapper.py
lastpass_hibp/main.py
lastpass_hibp-1.0.1.dist-info/LICENSE
lastpass_hibp-1.0.1.dist-info/METADATA
lastpass_hibp-1.0.1.dist-info/WHEEL
lastpass_hibp-1.0.1.dist-info/entry_points.txt
lastpass_hibp-1.0.1.dist-info/top_level.txt
lastpass_hibp-1.0.1.dist-info/zip-safe
lastpass_hibp-1.0.1.dist-info/RECORD
